sigkit/__init__.py
sigkit/core/__init__.py
sigkit/core/base.py
sigkit/datasets/__init__.py
sigkit/datasets/procedural.py
sigkit/impairments/__init__.py
sigkit/impairments/awgn.py
sigkit/impairments/base.py
sigkit/impairments/frequency_shift.py
sigkit/impairments/phase_shift.py
sigkit/metrics/__init__.py
sigkit/metrics/integrity.py
sigkit/metrics/visuals.py
sigkit/models/DataModule.py
sigkit/models/Module.py
sigkit/models/test.py
sigkit/models/train.py
sigkit/models/utils.py
sigkit/modem/__init__.py
sigkit/modem/base.py
sigkit/modem/fsk.py
sigkit/modem/psk.py
sigkit/transforms/__init__.py
sigkit/transforms/awgn.py
sigkit/transforms/frequency_shift.py
sigkit/transforms/phase_shift.py
sigkit/transforms/utils.py
sigkit-0.0.3.dist-info/licenses/LICENSE
sigkit-0.0.3.dist-info/METADATA
sigkit-0.0.3.dist-info/WHEEL
sigkit-0.0.3.dist-info/top_level.txt
sigkit-0.0.3.dist-info/RECORD
